{"urls": [
{"url": "file://tvbox/fongmi/adult.json","name":"FongMi AV Local"},
{"url": "file://tvbox/fongmi/fongmi.json","name":"FongMi Local"},
{"url": "file://tang/tang.json","name":"唐三Local"},
{"url": "file://JS/js.json","name":"JS专线Local"},
{"url": "file://py/py.json","name":"PY专线Local"},
{"url": "file://tvbox/xiaoya/xiaoya.json","name":"xiaoya"},
{"url": "file://tvbox/ptest/ptest.json","name":"ptest线路Box"},
{"url": "file://tvbox/00tv1/00tv1.json","name":"VPN4线路"},
{"url": "file://TVBox/meow2.json","name":"CH猫友️Local"},
{"url": "file://tvbox/XC/XC.json","name":"南风XC线路Local"},
{"url": "file://XYQ/XYQ.json","name":"XYQ线路local"},
{"url": "file://tvbox/fty/fty.json","name":"饭太硬线路Local"},
{"url": "file://tvbox/feimao/feimao.json","name":"肥猫线路"},
{"url": "file://tvbox/dxawi/dxawi.json","name":"dxwai"},
{"url": "file://tvboxhh/zbzdb.json","name":"MV Local"},
{"url": "file://tvboxhh/1110cr.json","name":"直播AV Local"},
{"url": "file://tvboxhh/duoduolive.json","name":"直播2Local"},
{"url": "file://TVlist/TVtoBox.txt","name":"直播2TV"},
{"url": "file://tvbox/jar/181.json","name":"彩蛋1Local"},
{"url": "file://tvbox/jar/182.json","name":"彩蛋2Local"},
{"url": "file://tvbox/jar/183.json","name":"彩蛋3Local"}

]
}